 {
        "id": 5012064,
        "name": "仇人的托付",
        "text": "你顺着小阿卜德留给你的地图寻去，找到了一间破破烂烂的棚屋。透过朽烂的墙板向内看去，里面寄宿着十几个穿着灰色袍服的僧人，想必这些就是苦修院的幸存者了。但他们的情况显然不容乐观。",       
        "tips": "",
        "mapping_id":8001261, 
        "once_new":1,
        "round_number": 1,
        "waiting_round":3,
        "waiting_round_end_action":[
        ],        
        "method_settlement": "",
        "auto_begin": 0, 
        "auto_result": 0,
        "location": "野外:[9,14]", 
        "icon": "rite_17", 
        "tag_tips": [        
        ],
        "tag_tips_up":{
        },
        "tips_text":[
            "你可以借机折断一张不高于青铜等级的奢靡卡。"
        ],
        "open_conditions": [
        ],
        "random_text":{
        },
        "random_text_up":{
        },
        "settlement_prior": [
            
        ],                
        "settlement": [
        ],               
        "settlement_extre": [
            {
                "condition": {

                },
                "result_title":"你想怎样？",
                "result_text": "你一露面，房间中间的老者就抄起了一根拨火棍，因为虚弱，没能成功举起，但他也没有撒手，而是目光炯炯地盯着你，怒声质问：“你们连孩子也不放过吗？”\n你没有理会他，环视了一下屋内的成员，基本都是些饥肠辘辘的孩童，脸上脏兮兮的，看你的眼神中充满了恐惧。\n是小阿卜德……阿莫叫我来的。\n你举了举手中的地图。\n老者拖着拨火棍来到你面前，从你手中接过地图，端详一番后才放松下来，他将地图还给你：“那孩子现在怎么样了？”\n他死了。\n老者沉重地叹了一口气：“我叫修邦，是命运神庙的住持，请原谅我的失礼，最近发生了很多事情……”",
                "result": 
                {
                },
                "action": {
                }
            },
            {
                "condition": {

                },
                "result_title":"你提议要帮助他们",
                "result_text": "你为孩子们带来了新鲜的食物，并邀请修邦一起用餐。在餐桌上，你提议资助他们重返圣地，并会找人去修缮基础设施，以后苦修院会纳入你的保护范围。你见老者并没有说话。\n你不相信？你问他。\n“无意冒犯，大人，但我知道任何好意都是有代价的。阿莫既然能请你这么做，自然对你有所许诺……我大概知道你想要什么，但也无需担心，如果您愿意帮助这些孩子的话，我会亲自确保将那份奖励送到您的手上。”对于一个三天没吃饭的人来说，修邦进食得极为克制。\n虽然还没拿到所谓的奖励，但至少，你终于知道小阿卜德的那股聪明劲是从哪来的了。",
                "result": 
                {
                },
                "action": {
                }
            },
            {
                "condition": {
                    "s3":1,
                    "s2.金币=":8
                },
                "result_title":"前进之路",
                "result_text": "你资助苦修院幸存者的事情公诸宫廷后，并没有引起多少反应，大家都觉得，这只不过又是你为了折断苏丹卡的大撒币行为之一。但你还是觉察到了一些不怀好意的目光。\n最好跟紧修邦的队伍。",
                "result": 
                {
                    "clean.s3":1,
                    "no_show":{"card":2000342}  //生成刺客
                },
                "action": {
                    "rite":5012065  //漫长归途

                }
            },
            {
                "condition": {
                    "!s3":1
                },
                "result_title":"保持警惕",
                "result_text": "你的资助行为发生在暗中，本就没有多少人知道苦修院的存在，即便是知道的人，也没有想过会有幸存者回到那里。修邦和孩子们很顺利地回家了。",
                "result": 
                {
                },
                "action": {
                    "event_on":5022077  //修缮神庙
                }
            }

        ],
        "cards_slot":
        {
            "s1":
            {
                "condition": 
                {
                    "type":"char",
                    "is":2100029
                },
                "open_adsorb":1,
                "is_key":0,
                "is_empty":0,
                "is_enemy":0,
                "text":"苦修士"
            },
            "s2":
            {
                "condition": 
                {
                    "type":"item",
                    "any":{
                    "cost.金币":[4,8],
                    "大餐": 1
                    }
                },
                "open_adsorb":0,
                "is_key":0,
                "is_empty":0,
                "is_enemy":0,
                "text":"你需要为孩子提供食物或者购买食物的钱"
            },
            "s3":
            {
                "condition": 
                {
                    "type":"sudan",
                    "奢靡":1,
                    "rare<=":2
                },
                "open_adsorb":0,
                "is_key":0,
                "is_empty":1,
                "is_enemy":0,
                "text":"如果想折断奢靡卡，就必须拿出8金币"
            }
        }
    } 