 {
        "id": 5012050,
        "name": "迷墙",
        "text": "为了使薇瑞娜摆脱“献祭者的印记”，你找到了纯净教会的祭司伊曼，他愿意为你提供帮助，亲自主持“天空之歌”的净化仪式。在仪式中，你们将会进入薇瑞娜的梦境，直面她的梦魇。这是一场不同寻常的战斗，务必做好准备。",       
        "tips": "",
        "mapping_id":8001068,
        "once_new":1,
        "round_number": 1,
        "waiting_round":3,
        "waiting_round_end_action":[
        {
            "condition":
            {
                
            },
            "result_title":"",
            "result_text": "在日复一日的梦魇和尖叫中，薇瑞娜日渐消沉。即便是阳光明媚的日子，她也不再欢笑，游离在梦境与现实的边境线，日益恍惚。",
            "result": 
            {   
            },
            "action":
            {

                "counter+9000055":1  //备用计数器
            }
        }
        ],        
        "method_settlement": "",
        "auto_begin": 1, 
        "auto_result": 0,
        "location": "自宅:[2,12]", 
        "icon": "rite_23", 
        "tag_tips": [
            "智慧"        
        ],
        "tag_tips_up":{
            "tips":["智慧"],
            "type":"normal_result"
        },
        "tips_text":[
            "“天空之歌”仪式会分成三个阶段展开",
            "失败意味着死亡"
        ],
        "open_conditions": [
        ],
        "random_text":{
        },
        "random_text_up":{
            "r1":{
                "text":"究竟谁才是真实的，在这个世界中存在真实吗？",
                "type":"normal_result",
                "type_tips":"你们的智慧为你们提供了完整的骰子点数",
                "low_target": 5,
                "low_target_tips": "你至少需要5点成功才能不受影响。"
            }
        },
        "settlement_prior": [
        ],                
        "settlement": [

        ],               
        "settlement_extre": [
                        {
                "condition": {
                },
                "result_title":"不要轻易说再见",
                "result_text": "“你回来了，”伊曼看见了你，你和你的药材。他已经在你的家宅中画好了仪式需要的符号和阵法，一个繁复精致的金色星形，每个角都对应着一个参加仪式的人。\n薇瑞娜坐在角落里，捧着一本图画书，目不停留地翻过一页又一页，那本书很快被翻到底，她又倒回来继续翻它，书页噼啪作响。伊曼对你说，“她一直在等你，想劝我放弃仪式，我拒绝了。”\n为什么，你问伊曼。\n“她叫你阿咪，不管你知不知道那是什么意思，她信任你，”伊曼从你手中接过药材，伏案清点起来，“信任一个人往往会遭致不好的结果，但辜负这份信任会让你失去更多。我相信你也是这么想的。”\n你在看什么？\n你走到薇瑞娜身边蹲下，薇瑞娜放下书，没有直接对上你的视线：“阿咪……伊曼说你们可能会死掉，在我的梦里。”\n不用理他，伊曼就是一个喜欢故弄玄虚的书呆子，你小声告诉薇瑞娜。\n伊曼从房间另一头传来刻意的咳嗽声，你无视了他，对薇瑞娜挤出一个鬼脸。女孩笑了出来，看着你，眼睛变得又大又黑，她希望从你的内心找到犹豫的证明，但她什么也没有找到。\n“阿咪很害怕，”薇瑞娜说。\n我才不会害怕，要进到薇瑞娜的梦里，和想象中的怪兽打架，就连苏丹也没有尝试过呢！\n你在说谎，薇瑞娜看出来了，但她没有说什么，只是张开细弱的双臂抱住了你……\n伊曼平静的声音打破了这份温情：“仪式可以开始了。”",
                "result": 
                {        
                },
                "action": {
                }
            },
            {
                "condition": {
                },
                "result_title":"迷墙",
                "result_text": "伴随着伊曼的药剂开始生效，你阖上眼睛，身子越来越沉，被柔软的地板吞没，向深层的黑暗坠去，越来越快，你应该被惊醒的，但是没有。\n在心脏即将跃出胸膛自寻出路之际，你与地面的接触无比坚硬。你头痛欲裂，口齿间充斥着铁锈的味道。环顾四周，你的同伴不在身边，你被一堵堵巨大的墨色石墙包围，一眼望不见它们有多高，参差林立的石墙上方是辽阔的漆黑天空，黯淡的星光明明灭灭。\n下意识地，你呼唤同伴们的姓名，但是没有人，甚至连回声都没有回应你。你必须找到离开的道路。\n……\n你已经忘记了自己何时来到此地，也数不清在迷宫中走过了多少岔口，你感觉不到身体的疲惫，但心灵却越来越憔悴衰微……\n不合时宜的尖叫撕破了寂静，是薇瑞娜！你一下子清醒过来，冲了过去。你看见两个身影出现在通道尽头，伊曼握着权杖，用尖锐的柄尾指着在地上苦苦哀求的女孩，他步步紧逼。\n“[player.name]，你不要过来，一步都不准动！”伊曼看都没有看你一眼，“她不是薇瑞娜，这就是我们一直在找的邪物。”\n女孩脸色惨白，手脚并用往后退去，一直被伊曼逼到墙根上，向你投出求救的眼神：“阿咪，告诉他我不是。”",
                "result": 
                {     
                },
                "action": {
                }
            },
            {
                "condition": {
                    "r1:s2.智慧+s3.智慧+s4.智慧+s5.智慧>=":[5,5]
                },
                "result_title":"关于信任的教诲",
                "result_text": "你的脚不自觉地往前踩了一步，伊曼感受到了你的动摇，他深呼了一口气，把权杖调转过来对准你，“那就来吧，我该如何向你证明？以避免我们之间的血战。”\n我信任你，尽管会遭致不好的结果，你一边说着，一边谨慎地摆出进攻的架势。\n“但辜负这份信任会让你失去更多。”伊曼说，你难以察觉地对伊曼点了点头，伊曼看到了。\n祭祀果断地回首向女孩刺去，在接触到她身体的一瞬间，女孩爆裂成无数猩红的触手，直扑向伊曼。但是你的速度更快，你已经撞开了伊曼，和他翻滚着直直掉了下去。",
                "result": 
                {     
                    "s3+智慧":1,
                    "s4+智慧":1,
                    "no_show":{
                        "clean.s1":1,
                        "card":2001070  //生成触手树到卡池
                    }
                },
                "action": {
                    "rite":5012051 //开启下一阶段任务
                }
            },
            {
                "condition": {
                    "r1:s2.智慧+s3.智慧+s4.智慧+s5.智慧<":[5,5]
                },
                "result_title":"那真是很抱歉了",
                "result_text": "你顾不得更多，冲向了伊曼。在你们扭打之际，身后的女孩缓缓站了起来，她的身体膨胀起来，脸上的五官开始错位，仿佛有什么东西要冲出肉囊。等你们发现的时候，已经为时已晚，一个巨大的红色怪物拦住了你们的退路，从口中绽放出无数鲜艳的触手，向你们袭来……\n“你个蠢货……”伊曼彻底躺下，放弃了抵抗。",
                "result": 
                {     
                    "clean.s4":1
                },
                "action": {
                    "over":804  //对不起，薇瑞娜
                }
            }
        ],
        "cards_slot":
        {
            "s1":
                {
                    "condition": 
                    {
                        "type":"item",
                        "is":2100021
                    },
                    "open_adsorb":1,
                    "is_key":0,
                    "is_empty":0,
                    "is_enemy":0,
                    "text":"献祭者的烙印"
                },
            "s2":
                {
                    "condition": 
                    {
                        "type":"char",
                        "薇瑞娜":1
                    },
                    "open_adsorb":1,
                    "is_key":0,
                    "is_empty":0,
                    "is_enemy":0,
                    "text":"梦境的主人",
                    "pops":[
                    {
                        "condition":{
                            "s4":1
                        },
                        "action":{
                            "choose":{
                                "pop.5012050_s2_1.self":"阿咪，再等等……"
                            }
                        }
                    }
                ]
                },
            "s3":
                {
                    "condition": 
                    {
                        "type":"char",
                        "all":{
                        "is":2000021,
                        "捕梦人":1
                        }

                    },
                    "open_adsorb":1,
                    "is_key":0,
                    "is_empty":0,
                    "is_enemy":0,
                    "text":"主持仪式的祭司",
                    "pops":[
                    {
                        "condition":{
                            "s4": 1
                        },
                        "action":{
                            "choose":{
                                "pop.5012050_s3_1.self":"我们可以开始了"
                            }
                        }
                    }
                ]
                },
            "s4":
                {
                    "condition": 
                    {
                        "type":"char",
                        "all":{
                        "主角":1,
                        "捕梦人":1
                        }

                    },
                    "open_adsorb":0,
                    "is_key":0,
                    "is_empty":0,
                    "is_enemy":0,
                    "text":"你必须亲自参加仪式",
                    "pops":[
                    {
                        "condition":{
                        },
                        "action":{
                            "choose":{
                                "pop.5012050_s4_1.self":"你会没事的"
                            }
                        }
                    }
                ]
                },
                
            "s5":
                {
                    "condition": 
                    {
                        "type":"item",
                        "消耗品":1
                    },
                    "open_adsorb":0,
                    "is_key":0,
                    "is_empty":1,
                    "is_enemy":0,
                    "text":"辅助你们完成仪式的道具"
                }
        }
    } 